{
  "OPT8_iv_rv_term_d10": {
    "id": "om9ZMrk6",
    "sharpe": -0.65,
    "fitness": -0.23,
    "turnover": 0.2314,
    "returns": -0.028,
    "sub_sharpe": -0.63,
    "ret_to": -0.12100259291270528,
    "sha_ok": false,
    "fit_ok": false,
    "sub_ok": false,
    "all_pass": false,
    "expression": "my_group=bucket(rank(cap),range='0.1,1,0.1');iv_rv=ts_zscore(implied_volatility_mean_30-historical_volatility_30,126);term=ts_zscore(implied_volatility_mean_30-implied_volatility_mean_180,126);raw=-rank(iv_rv)*rank(term);group_neutralize(raw,my_group)"
  },
  "OPT8_vrp_only_d10": {
    "id": "1Yn0E9bW",
    "sharpe": -0.51,
    "fitness": -0.18,
    "turnover": 0.1839,
    "returns": -0.023,
    "sub_sharpe": -0.11,
    "ret_to": -0.1250679717237629,
    "sha_ok": false,
    "fit_ok": false,
    "sub_ok": false,
    "all_pass": false,
    "expression": "my_group=bucket(rank(cap),range='0.1,1,0.1');iv_rv=ts_zscore(implied_volatility_mean_30-historical_volatility_30,126);raw=-rank(iv_rv);group_neutralize(raw,my_group)"
  },
  "OPT8_term_twist_d10": {
    "id": "zqJep9W8",
    "sharpe": -0.61,
    "fitness": -0.18,
    "turnover": 0.3244,
    "returns": -0.0271,
    "sub_sharpe": -0.69,
    "ret_to": -0.08353884093711467,
    "sha_ok": false,
    "fit_ok": false,
    "sub_ok": false,
    "all_pass": false,
    "expression": "my_group=bucket(rank(cap),range='0.1,1,0.1');slope=implied_volatility_mean_30-implied_volatility_mean_180;twist=ts_zscore(ts_delta(slope,10),252);carry=ts_zscore(slope,126);raw=-rank(twist)*rank(carry);group_neutralize(raw,my_group)"
  },
  "OPT8_skew_shock_d10": {
    "id": "pw13O5x3",
    "sharpe": 0.46,
    "fitness": 0.06,
    "turnover": 0.6929,
    "returns": 0.0137,
    "sub_sharpe": 0.06,
    "ret_to": 0.019771972867657674,
    "sha_ok": false,
    "fit_ok": false,
    "sub_ok": false,
    "all_pass": false,
    "expression": "my_group=bucket(rank(cap),range='0.1,1,0.1');skew_chg=ts_zscore(ts_delta(implied_volatility_mean_skew_30,5),252);raw=-rank(skew_chg);group_neutralize(raw,my_group)"
  },
  "OPT8_put_call_d10": {
    "id": "xAm5gWeb",
    "sharpe": 0.15,
    "fitness": 0.01,
    "turnover": 0.6458,
    "returns": 0.0039,
    "sub_sharpe": -0.39,
    "ret_to": 0.006039021368844843,
    "sha_ok": false,
    "fit_ok": false,
    "sub_ok": false,
    "all_pass": false,
    "expression": "my_group=bucket(rank(cap),range='0.1,1,0.1');pc_gap=implied_volatility_put_30-implied_volatility_call_30;pc_chg=ts_zscore(ts_delta(pc_gap,5),252);raw=-rank(pc_chg);group_neutralize(raw,my_group)"
  },
  "OPT8_parkinson_d10": {
    "id": "e7qEJlEM",
    "sharpe": -0.42,
    "fitness": -0.17,
    "turnover": 0.1229,
    "returns": -0.0197,
    "sub_sharpe": 0.04,
    "ret_to": -0.16029292107404394,
    "sha_ok": false,
    "fit_ok": false,
    "sub_ok": false,
    "all_pass": false,
    "expression": "my_group=bucket(rank(cap),range='0.1,1,0.1');pk_gap=ts_zscore(parkinson_volatility_30-historical_volatility_30,126);raw=-rank(pk_gap);group_neutralize(raw,my_group)"
  },
  "OPT8_vrp_term_grp_d10": {
    "id": "A1OEdqwg",
    "sharpe": -1.05,
    "fitness": -0.55,
    "turnover": 0.1761,
    "returns": -0.0477,
    "sub_sharpe": -0.65,
    "ret_to": -0.2708688245315162,
    "sha_ok": false,
    "fit_ok": false,
    "sub_ok": false,
    "all_pass": false,
    "expression": "my_group=bucket(rank(cap),range='0.1,1,0.1');iv_rv=ts_zscore(implied_volatility_mean_30-historical_volatility_30,126);term=ts_zscore(implied_volatility_mean_30-implied_volatility_mean_90,126);raw=-group_rank(iv_rv,my_group)*group_rank(term,my_group);group_neutralize(raw,my_group)"
  },
  "OPT8_vrp_90d_d10": {
    "id": "leR1ZrMO",
    "sharpe": -0.86,
    "fitness": -0.34,
    "turnover": 0.2129,
    "returns": -0.0338,
    "sub_sharpe": -0.49,
    "ret_to": -0.15875998121183652,
    "sha_ok": false,
    "fit_ok": false,
    "sub_ok": false,
    "all_pass": false,
    "expression": "my_group=bucket(rank(cap),range='0.1,1,0.1');iv_rv=ts_zscore(implied_volatility_mean_90-historical_volatility_90,126);term=ts_zscore(implied_volatility_mean_90-implied_volatility_mean_360,126);raw=-rank(iv_rv)*rank(term);group_neutralize(raw,my_group)"
  },
  "OPT8_iv_momentum_d10": {
    "id": "0mK5WR62",
    "sharpe": -0.89,
    "fitness": -0.26,
    "turnover": 0.4534,
    "returns": -0.0386,
    "sub_sharpe": -0.69,
    "ret_to": -0.08513453903837671,
    "sha_ok": false,
    "fit_ok": false,
    "sub_ok": false,
    "all_pass": false,
    "expression": "my_group=bucket(rank(cap),range='0.1,1,0.1');iv_chg=ts_zscore(ts_delta(implied_volatility_mean_30,5),126);raw=-rank(iv_chg);group_neutralize(raw,my_group)"
  },
  "OPT8_vrp_skew_d10": {
    "id": "om9ZeGYb",
    "sharpe": -0.21,
    "fitness": -0.04,
    "turnover": 0.3004,
    "returns": -0.0086,
    "sub_sharpe": 0.04,
    "ret_to": -0.02862849533954727,
    "sha_ok": false,
    "fit_ok": false,
    "sub_ok": false,
    "all_pass": false,
    "expression": "my_group=bucket(rank(cap),range='0.1,1,0.1');iv_rv=ts_zscore(implied_volatility_mean_30-historical_volatility_30,126);skew=ts_zscore(implied_volatility_mean_skew_30,126);raw=-rank(iv_rv)*rank(skew);group_neutralize(raw,my_group)"
  },
  "OPT8_iv_rv_term_d5": {
    "id": "vRJP0qKd",
    "sharpe": -0.81,
    "fitness": -0.27,
    "turnover": 0.3044,
    "returns": -0.0349,
    "sub_sharpe": -0.77,
    "ret_to": -0.11465177398160316,
    "sha_ok": false,
    "fit_ok": false,
    "sub_ok": false,
    "all_pass": false,
    "expression": "my_group=bucket(rank(cap),range='0.1,1,0.1');iv_rv=ts_zscore(implied_volatility_mean_30-historical_volatility_30,126);term=ts_zscore(implied_volatility_mean_30-implied_volatility_mean_180,126);raw=-rank(iv_rv)*rank(term);group_neutralize(raw,my_group)"
  },
  "OPT8_iv_rv_term_d20": {
    "id": "rKr8kLJE",
    "sharpe": -0.54,
    "fitness": -0.19,
    "turnover": 0.192,
    "returns": -0.0226,
    "sub_sharpe": -0.63,
    "ret_to": -0.11770833333333332,
    "sha_ok": false,
    "fit_ok": false,
    "sub_ok": false,
    "all_pass": false,
    "expression": "my_group=bucket(rank(cap),range='0.1,1,0.1');iv_rv=ts_zscore(implied_volatility_mean_30-historical_volatility_30,126);term=ts_zscore(implied_volatility_mean_30-implied_volatility_mean_180,126);raw=-rank(iv_rv)*rank(term);group_neutralize(raw,my_group)"
  },
  "OPT8_term_twist_d5": {
    "id": "E5rx3vdR",
    "sharpe": -0.77,
    "fitness": -0.23,
    "turnover": 0.405,
    "returns": -0.0346,
    "sub_sharpe": -0.8,
    "ret_to": -0.08543209876543209,
    "sha_ok": false,
    "fit_ok": false,
    "sub_ok": false,
    "all_pass": false,
    "expression": "my_group=bucket(rank(cap),range='0.1,1,0.1');slope=implied_volatility_mean_30-implied_volatility_mean_180;twist=ts_zscore(ts_delta(slope,10),252);carry=ts_zscore(slope,126);raw=-rank(twist)*rank(carry);group_neutralize(raw,my_group)"
  }
}